{"py/object": "rasa.core.featurizers.tracker_featurizers.IntentMaxHistoryTrackerFeaturizer", "state_featurizer": {"py/object": "rasa.core.featurizers.single_state_featurizer.IntentTokenizerSingleStateFeaturizer", "_default_feature_states": {"intent": {"add_3d_geometry": 0, "add_connectors": 1, "add_ellipsoid": 2, "add_spectral_data_dialog": 3, "add_sphere": 4, "affirm": 5, "ask_tree_view": 6, "back": 7, "bot_challenge": 8, "copy_paste_spectral_data": 9, "create_cylindrical_fairing_volume": 10, "create_junction": 11, "create_spacecraft_volume": 12, "cut_shape": 13, "deny": 14, "goodbye": 15, "greet": 16, "hide_objects": 17, "input_spectral_data": 18, "inquire_frequency_domain": 19, "inquire_frequency_vector": 20, "mood_great": 21, "mood_unhappy": 22, "nlu_fallback": 23, "out_of_scope": 24, "pan_model": 25, "restart": 26, "rotate_model": 27, "scroll_in_out": 28, "session_start": 29, "specify_frequency_sample": 30, "wire_constructions": 31}, "action_name": {"action_listen": 0, "action_restart": 1, "action_session_start": 2, "action_default_fallback": 3, "action_deactivate_loop": 4, "action_revert_fallback_events": 5, "action_default_ask_affirmation": 6, "action_default_ask_rephrase": 7, "action_two_stage_fallback": 8, "action_unlikely_intent": 9, "action_back": 10, "...": 11, "action_extract_slots": 12, "utter_create_cylindrical_fairing_volume": 13, "utter_create_spacecraft_volume": 14, "utter_cut_shape": 15, "utter_add_ellipsoid": 16, "utter_add_sphere": 17, "utter_pan_model": 18, "utter_scroll_in_out": 19, "utter_rotate_model": 20, "utter_hide_objects": 21, "utter_add_3d_geometry": 22, "utter_wire_constructions": 23, "utter_add_connectors": 24, "utter_create_junction": 25, "utter_ask_tree_view": 26, "utter_cheer_up": 27, "utter_did_that_help": 28, "utter_explain_add_spectral_data_dialog": 29, "utter_explain_copy_paste_spectral_data": 30, "utter_explain_frequency_sample": 31, "utter_explain_frequency_vector": 32, "utter_explain_input_spectral_data": 33, "utter_goodbye": 34, "utter_greet": 35, "utter_happy": 36, "utter_iamabot": 37}, "entities": {}, "slots": {}, "active_loop": {}}, "action_texts": [], "entity_tag_specs": []}, "max_history": 5, "remove_duplicates": true}